poetry_clovers_plugin/core/__init__.py
poetry_clovers_plugin/core/create.py
poetry_clovers_plugin/core/main.py
poetry_clovers_plugin/core/new.py
poetry_clovers_plugin/core/plugin.py
poetry_clovers_plugin/core/template/__init__.py
poetry_clovers_plugin/core/template/adapter/__init__.py
poetry_clovers_plugin/core/template/adapter/main.py
poetry_clovers_plugin/core/template/bot/clovers.toml
poetry_clovers_plugin/core/template/bot/clovers_library/plugins/save_config.py
poetry_clovers_plugin/core/template/client/__init__.py
poetry_clovers_plugin/core/template/client/config.py
poetry_clovers_plugin/core/template/client/main.py
poetry_clovers_plugin/core/template/plugin/__init__.py
poetry_clovers_plugin/core/template/plugin/clovers.py
poetry_clovers_plugin/core/template/plugin/config.py
poetry_clovers_plugin/core/template/plugin/main.py
poetry_clovers_plugin/plugin.py
poetry_clovers_plugin/scripts.py
poetry_clovers_plugin-0.0.3.dist-info/entry_points.txt
poetry_clovers_plugin-0.0.3.dist-info/METADATA
poetry_clovers_plugin-0.0.3.dist-info/WHEEL
poetry_clovers_plugin-0.0.3.dist-info/RECORD
