Metadata-Version: 2.3
Name: poetry-clovers-plugin
Version: 0.0.3
Summary: 
Author: KarisAya
Author-email: karisaya@foxmail.com
Requires-Python: >=3.12,<4.0.0
Classifier: Programming Language :: Python :: 3
Classifier: Programming Language :: Python :: 3.12
Classifier: Programming Language :: Python :: 3.13
Requires-Dist: clovers (>=0.4.6,<1.0.0)
Requires-Dist: poetry (>=2.0.0,<3.0.0)
